CHANGES.md
MANIFEST.in
README.md
UNLICENSE
setup.py
src/pyramid_redis/__init__.py
src/pyramid_redis/config.py
src/pyramid_redis/hooks.py
src/pyramid_redis/turnstile.py
src/pyramid_redis.egg-info/PKG-INFO
src/pyramid_redis.egg-info/SOURCES.txt
src/pyramid_redis.egg-info/dependency_links.txt
src/pyramid_redis.egg-info/not-zip-safe
src/pyramid_redis.egg-info/requires.txt
src/pyramid_redis.egg-info/top_level.txt